MANIFEST.in
setup.py
pyphant/__init__.py
pyphant.egg-info/PKG-INFO
pyphant.egg-info/SOURCES.txt
pyphant.egg-info/dependency_links.txt
pyphant.egg-info/entry_points.txt
pyphant.egg-info/requires.txt
pyphant.egg-info/top_level.txt
pyphant/core/AstTransformers.py
pyphant/core/CompositeWorker.py
pyphant/core/Connectors.py
pyphant/core/DataContainer.py
pyphant/core/Emd5Src.py
pyphant/core/EventDispatcher.py
pyphant/core/FMFGen.py
pyphant/core/FieldContainer.py
pyphant/core/H5FileHandler.py
pyphant/core/Helpers.py
pyphant/core/KnowledgeManager.py
pyphant/core/KnowledgeNode.py
pyphant/core/LoadFMF.py
pyphant/core/Param.py
pyphant/core/PyTablesPersister.py
pyphant/core/RoutingHTTPServer.py
pyphant/core/SQLiteWrapper.py
pyphant/core/UpdateManager.py
pyphant/core/WebInterface.py
pyphant/core/Worker.py
pyphant/core/WorkerRegistry.py
pyphant/core/WriteFMF.py
pyphant/core/__init__.py
pyphant/core/bottle.py
pyphant/core/singletonmixin.py
pyphant/mplbackend/__init__.py
pyphant/quantities/ParseQuantities.py
pyphant/quantities/PhysicalQuantities.py
pyphant/quantities/__init__.py
pyphant/tests/Helpers.py
pyphant/tests/TestChart.py
pyphant/tests/TestCompositeWorker.py
pyphant/tests/TestDataContainer.py
pyphant/tests/TestEmd5Source.py
pyphant/tests/TestEventDispatcher.py
pyphant/tests/TestH5FileHandler.py
pyphant/tests/TestHelpers.py
pyphant/tests/TestImageVisualizer.py
pyphant/tests/TestInitRecipe.py
pyphant/tests/TestKnowledgeManager.py
pyphant/tests/TestKnowledgeNode.py
pyphant/tests/TestLoadFMF.py
pyphant/tests/TestParam.py
pyphant/tests/TestParseQuantities.py
pyphant/tests/TestPyTablesPersister.py
pyphant/tests/TestQuantities.py
pyphant/tests/TestSQLiteWrapper.py
pyphant/tests/TestTimestamp.py
pyphant/tests/__init__.py
pyphant/tests/resources/fmf/dep.fmf
pyphant/tests/resources/fmf/hash_test.fmf
pyphant/tests/resources/fmf/multitable.fmf
pyphant/tests/resources/fmf/onecolumn.fmf
pyphant/tests/resources/fmf/onerow.fmf
pyphant/tests/resources/fmf/onerow_dep.fmf
pyphant/tests/resources/fmf/onevalue.fmf
pyphant/tests/resources/fmf/semi_test.fmf
pyphant/visualizers/Chart.py
pyphant/visualizers/ConfigurablePlot.py
pyphant/visualizers/External.py
