Metadata-Version: 1.0
Name: pyphant
Version: 1.0b3
Summary: Workflow modelling app
Home-page: http://pyphant.sourceforge.net/
Author: Alexander Held
Author-email: alexander.held@fmf.uni-freiburg.de
License: BSD
Platform: UNKNOWN
